src/InterfaceGraphique.py
src/PageAnimation.py
src/PageLectureConfiguration.py
src/PageLectureDonnees.py
src/PageResultats.py
src/__init__.py
src/intelligenceArtificielle/Autoencodeur.py
src/intelligenceArtificielle/AutoencodeurDeterministe.py
src/intelligenceArtificielle/AutoencodeurNonDeterministe.py
src/intelligenceArtificielle/Entrainement.py
src/intelligenceArtificielle/GenerateurArbres.py
src/intelligenceArtificielle/Genetique.py
src/intelligenceArtificielle/Outils.py
src/intelligenceArtificielle/__init__.py
src/intelligenceArtificielle/structureDonnees/Arbre.py
src/intelligenceArtificielle/structureDonnees/Coefficients.py
src/intelligenceArtificielle/structureDonnees/Feuille.py
src/intelligenceArtificielle/structureDonnees/Noeud.py
src/intelligenceArtificielle/structureDonnees/Parallele.py
src/intelligenceArtificielle/structureDonnees/Serie.py
src/intelligenceArtificielle/structureDonnees/SunRiseException.py
src/intelligenceArtificielle/structureDonnees/__init__.py
sunrise.py
sunriseces-0.0.3.dist-info/entry_points.txt
sunriseces-0.0.3.dist-info/LICENSE
sunriseces-0.0.3.dist-info/WHEEL
sunriseces-0.0.3.dist-info/METADATA
sunriseces-0.0.3.dist-info/RECORD
