Metadata-Version: 2.1
Name: sunriseces
Version: 0.0.3
Summary: Outils d'inférence de paramètres pour thermique de bâtiments
Home-page: https://sites.google.com/view/2019-2020-gr12/home
License: GPL-3.0-or-later
Keywords: sunrise,machine-learning,thermal,modelisation-verification,mines-de-paris
Author: Voir GitHub
Requires-Python: >=3.7,<4.0
Classifier: License :: OSI Approved :: GNU General Public License v3 or later (GPLv3+)
Classifier: Natural Language :: French
Classifier: Operating System :: Microsoft :: Windows :: Windows 10
Classifier: Operating System :: POSIX
Classifier: Programming Language :: Python :: 3
Classifier: Programming Language :: Python :: 3.7
Classifier: Programming Language :: Python :: 3.8
Classifier: Topic :: Scientific/Engineering :: Artificial Intelligence
Classifier: Topic :: Scientific/Engineering :: Physics
Requires-Dist: keras (>=2.3.1,<3.0.0)
Requires-Dist: matplotlib (>=3.2.1,<4.0.0)
Requires-Dist: numpy (>=1.18.3,<2.0.0)
Requires-Dist: scipy (>=1.4.1,<2.0.0)
Requires-Dist: tensorflow (>=2.2.0,<3.0.0)
Project-URL: Repository, https://github.com/18tbr/sunrise-refonte
